uplink_python/__init__.py
uplink_python/access.py
uplink_python/download.py
uplink_python/errors.py
uplink_python/hello_storj.py
uplink_python/module_classes.py
uplink_python/module_def.py
uplink_python/project.py
uplink_python/uplink.py
uplink_python/upload.py
uplink_python-1.1.0.1.dist-info/LICENSE
uplink_python-1.1.0.1.dist-info/METADATA
uplink_python-1.1.0.1.dist-info/WHEEL
uplink_python-1.1.0.1.dist-info/top_level.txt
uplink_python-1.1.0.1.dist-info/RECORD
