Metadata-Version: 2.1
Name: uplink-python
Version: 1.1.0.1
Summary: Python-native language binding for uplink to communicate with the Storj network.
Home-page: https://github.com/storj-thirdparty/uplink-python
Author: Utropicmedia
Author-email: development@utropicmedia.com
License: Apache Software License
Platform: UNKNOWN
Classifier: Intended Audience :: Developers
Classifier: Programming Language :: Python :: 3
Classifier: License :: OSI Approved :: Apache Software License
Classifier: Operating System :: OS Independent
Classifier: Topic :: Software Development :: Build Tools
Requires-Python: >=3.4
Requires-Dist: wheel
